[
  {
    "bbox": [
      [
        60.0,
        22.0
      ],
      [
        88.0,
        22.0
      ],
      [
        88.0,
        78.0
      ],
      [
        60.0,
        78.0
      ]
    ],
    "text": "丘",
    "confidence": 0.006388270130967877
  },
  {
    "bbox": [
      [
        129.0,
        19.0
      ],
      [
        273.0,
        19.0
      ],
      [
        273.0,
        83.0
      ],
      [
        129.0,
        83.0
      ]
    ],
    "text": "三窆1+",
    "confidence": 0.0006318822270259261
  },
  {
    "bbox": [
      [
        354.0,
        24.0
      ],
      [
        384.0,
        24.0
      ],
      [
        384.0,
        82.0
      ],
      [
        354.0,
        82.0
      ]
    ],
    "text": "藝",
    "confidence": 0.16071981143719327
  },
  {
    "bbox": [
      [
        459.0,
        17.0
      ],
      [
        565.0,
        17.0
      ],
      [
        565.0,
        83.0
      ],
      [
        459.0,
        83.0
      ]
    ],
    "text": "存_",
    "confidence": 0.0019863480534555527
  },
  {
    "bbox": [
      [
        610.0,
        26.0
      ],
      [
        636.0,
        26.0
      ],
      [
        636.0,
        78.0
      ],
      [
        610.0,
        78.0
      ]
    ],
    "text": "三",
    "confidence": 0.8570010653031126
  },
  {
    "bbox": [
      [
        62.0,
        84.0
      ],
      [
        88.0,
        84.0
      ],
      [
        88.0,
        162.0
      ],
      [
        62.0,
        162.0
      ]
    ],
    "text": "劣",
    "confidence": 0.030659779940550358
  },
  {
    "bbox": [
      [
        82.0,
        9.0
      ],
      [
        252.0,
        9.0
      ],
      [
        252.0,
        181.0
      ],
      [
        82.0,
        181.0
      ]
    ],
    "text": "1",
    "confidence": 0.00040432085494068737
  },
  {
    "bbox": [
      [
        254.0,
        4.0
      ],
      [
        476.0,
        4.0
      ],
      [
        476.0,
        257.0
      ],
      [
        254.0,
        257.0
      ]
    ],
    "text": "輜",
    "confidence": 0.0049805622964705365
  },
  {
    "bbox": [
      [
        462.0,
        82.0
      ],
      [
        488.0,
        82.0
      ],
      [
        488.0,
        162.0
      ],
      [
        462.0,
        162.0
      ]
    ],
    "text": "%",
    "confidence": 0.8398217614792749
  },
  {
    "bbox": [
      [
        536.0,
        78.0
      ],
      [
        608.0,
        78.0
      ],
      [
        608.0,
        224.0
      ],
      [
        536.0,
        224.0
      ]
    ],
    "text": "",
    "confidence": 0.0
  },
  {
    "bbox": [
      [
        65.0,
        139.0
      ],
      [
        269.0,
        139.0
      ],
      [
        269.0,
        247.0
      ],
      [
        65.0,
        247.0
      ]
    ],
    "text": "38332",
    "confidence": 0.0016505934342137569
  },
  {
    "bbox": [
      [
        401.0,
        155.0
      ],
      [
        467.0,
        155.0
      ],
      [
        467.0,
        253.0
      ],
      [
        401.0,
        253.0
      ]
    ],
    "text": ";",
    "confidence": 0.13541636742474683
  },
  {
    "bbox": [
      [
        476.0,
        153.0
      ],
      [
        506.0,
        153.0
      ],
      [
        506.0,
        310.0
      ],
      [
        476.0,
        310.0
      ]
    ],
    "text": "",
    "confidence": 0.0
  },
  {
    "bbox": [
      [
        551.0,
        161.0
      ],
      [
        577.0,
        161.0
      ],
      [
        577.0,
        260.0
      ],
      [
        551.0,
        260.0
      ]
    ],
    "text": "*",
    "confidence": 0.03570211459120376
  },
  {
    "bbox": [
      [
        612.0,
        152.0
      ],
      [
        644.0,
        152.0
      ],
      [
        644.0,
        252.0
      ],
      [
        612.0,
        252.0
      ]
    ],
    "text": "",
    "confidence": 0.0
  },
  {
    "bbox": [
      [
        57.0,
        231.0
      ],
      [
        257.0,
        231.0
      ],
      [
        257.0,
        415.0
      ],
      [
        57.0,
        415.0
      ]
    ],
    "text": "",
    "confidence": 0.0
  },
  {
    "bbox": [
      [
        242.0,
        429.0
      ],
      [
        314.0,
        429.0
      ],
      [
        314.0,
        548.0
      ],
      [
        242.0,
        548.0
      ]
    ],
    "text": "**",
    "confidence": 0.00572424575021739
  },
  {
    "bbox": [
      [
        386.0,
        426.0
      ],
      [
        582.0,
        426.0
      ],
      [
        582.0,
        548.0
      ],
      [
        386.0,
        548.0
      ]
    ],
    "text": "@8",
    "confidence": 0.00016415212224189164
  },
  {
    "bbox": [
      [
        620.0,
        434.0
      ],
      [
        648.0,
        434.0
      ],
      [
        648.0,
        478.0
      ],
      [
        620.0,
        478.0
      ]
    ],
    "text": "複",
    "confidence": 0.016228059537440664
  },
  {
    "bbox": [
      [
        350.0,
        520.0
      ],
      [
        374.0,
        520.0
      ],
      [
        374.0,
        558.0
      ],
      [
        350.0,
        558.0
      ]
    ],
    "text": "注",
    "confidence": 0.0010679142978320538
  },
  {
    "bbox": [
      [
        354.0,
        564.0
      ],
      [
        378.0,
        564.0
      ],
      [
        378.0,
        616.0
      ],
      [
        354.0,
        616.0
      ]
    ],
    "text": "",
    "confidence": 0.0
  },
  {
    "bbox": [
      [
        608.7234053683178,
        80.01277797783214
      ],
      [
        635.3947672193297,
        77.02608694771641
      ],
      [
        645.2765946316822,
        193.98722202216786
      ],
      [
        619.6052327806703,
        195.9739130522836
      ]
    ],
    "text": "",
    "confidence": 0.0
  },
  {
    "bbox": [
      [
        239.61715037342296,
        81.01836388359888
      ],
      [
        269.6808275859199,
        78.05836660783241
      ],
      [
        279.382849626577,
        192.98163611640112
      ],
      [
        249.31917241408016,
        195.94163339216757
      ]
    ],
    "text": "#",
    "confidence": 0.6475900820670546
  },
  {
    "bbox": [
      [
        494.74247088800814,
        82.00829876412617
      ],
      [
        523.2449382584639,
        78.00750638703822
      ],
      [
        546.2575291119919,
        244.99170123587382
      ],
      [
        518.7550617415361,
        248.9924936129618
      ]
    ],
    "text": "",
    "confidence": 0.0
  },
  {
    "bbox": [
      [
        346.77049365363143,
        83.00658957318728
      ],
      [
        379.2194492153155,
        79.0060242812584
      ],
      [
        402.22950634636857,
        264.9934104268127
      ],
      [
        370.7805507846845,
        268.9939757187416
      ]
    ],
    "text": "",
    "confidence": 0.0
  }
]