[
  {
    "bbox": [
      [
        218.0,
        138.0
      ],
      [
        338.0,
        138.0
      ],
      [
        338.0,
        164.0
      ],
      [
        218.0,
        164.0
      ]
    ],
    "text": "位菸甄之旬不0人矣",
    "confidence": 0.0020648857472399798
  },
  {
    "bbox": [
      [
        579.0,
        144.0
      ],
      [
        632.0,
        144.0
      ],
      [
        632.0,
        170.0
      ],
      [
        579.0,
        170.0
      ]
    ],
    "text": "貼野保",
    "confidence": 1.6874078280855795e-05
  },
  {
    "bbox": [
      [
        215.0,
        153.0
      ],
      [
        341.0,
        153.0
      ],
      [
        341.0,
        196.0
      ],
      [
        215.0,
        196.0
      ]
    ],
    "text": "蠶",
    "confidence": 0.00024488386134408416
  },
  {
    "bbox": [
      [
        336.0,
        138.0
      ],
      [
        388.0,
        138.0
      ],
      [
        388.0,
        214.0
      ],
      [
        336.0,
        214.0
      ]
    ],
    "text": "塑",
    "confidence": 0.004852161713462033
  },
  {
    "bbox": [
      [
        172.0,
        117.0
      ],
      [
        220.0,
        117.0
      ],
      [
        220.0,
        348.0
      ],
      [
        172.0,
        348.0
      ]
    ],
    "text": "",
    "confidence": 0.0
  },
  {
    "bbox": [
      [
        215.0,
        187.0
      ],
      [
        307.0,
        187.0
      ],
      [
        307.0,
        249.0
      ],
      [
        215.0,
        249.0
      ]
    ],
    "text": "鑑%",
    "confidence": 0.00010257783931520942
  },
  {
    "bbox": [
      [
        249.0,
        187.0
      ],
      [
        331.0,
        187.0
      ],
      [
        331.0,
        247.0
      ],
      [
        249.0,
        247.0
      ]
    ],
    "text": "璞轎#",
    "confidence": 0.00015611216050899309
  },
  {
    "bbox": [
      [
        426.0,
        120.0
      ],
      [
        526.0,
        120.0
      ],
      [
        526.0,
        307.0
      ],
      [
        426.0,
        307.0
      ]
    ],
    "text": "",
    "confidence": 0.0
  },
  {
    "bbox": [
      [
        59.0,
        223.0
      ],
      [
        75.0,
        223.0
      ],
      [
        75.0,
        321.0
      ],
      [
        59.0,
        321.0
      ]
    ],
    "text": "",
    "confidence": 0.0
  },
  {
    "bbox": [
      [
        69.0,
        128.0
      ],
      [
        180.0,
        128.0
      ],
      [
        180.0,
        531.0
      ],
      [
        69.0,
        531.0
      ]
    ],
    "text": "",
    "confidence": 0.0
  },
  {
    "bbox": [
      [
        207.0,
        249.0
      ],
      [
        349.0,
        249.0
      ],
      [
        349.0,
        389.0
      ],
      [
        207.0,
        389.0
      ]
    ],
    "text": "",
    "confidence": 0.0
  },
  {
    "bbox": [
      [
        339.0,
        241.0
      ],
      [
        359.0,
        241.0
      ],
      [
        359.0,
        295.0
      ],
      [
        339.0,
        295.0
      ]
    ],
    "text": "釜",
    "confidence": 0.006206099857028136
  },
  {
    "bbox": [
      [
        345.0,
        291.0
      ],
      [
        363.0,
        291.0
      ],
      [
        363.0,
        327.0
      ],
      [
        345.0,
        327.0
      ]
    ],
    "text": "訖",
    "confidence": 0.0007405926719079338
  },
  {
    "bbox": [
      [
        337.0,
        108.0
      ],
      [
        586.0,
        108.0
      ],
      [
        586.0,
        550.0
      ],
      [
        337.0,
        550.0
      ]
    ],
    "text": "棻",
    "confidence": 0.00029731288247682175
  },
  {
    "bbox": [
      [
        275.0,
        375.0
      ],
      [
        335.0,
        375.0
      ],
      [
        335.0,
        395.0
      ],
      [
        275.0,
        395.0
      ]
    ],
    "text": "匹二首迂則",
    "confidence": 0.0005117241885828575
  },
  {
    "bbox": [
      [
        581.0,
        381.0
      ],
      [
        605.0,
        381.0
      ],
      [
        605.0,
        401.0
      ],
      [
        581.0,
        401.0
      ]
    ],
    "text": "筋",
    "confidence": 0.007975374775640809
  },
  {
    "bbox": [
      [
        57.0,
        321.0
      ],
      [
        75.0,
        321.0
      ],
      [
        75.0,
        503.0
      ],
      [
        57.0,
        503.0
      ]
    ],
    "text": "",
    "confidence": 0.0
  },
  {
    "bbox": [
      [
        178.0,
        336.0
      ],
      [
        210.0,
        336.0
      ],
      [
        210.0,
        480.0
      ],
      [
        178.0,
        480.0
      ]
    ],
    "text": "奐",
    "confidence": 0.00369591264999386
  },
  {
    "bbox": [
      [
        237.0,
        385.0
      ],
      [
        361.0,
        385.0
      ],
      [
        361.0,
        449.0
      ],
      [
        237.0,
        449.0
      ]
    ],
    "text": "轄美",
    "confidence": 0.0001385285379666379
  },
  {
    "bbox": [
      [
        430.0,
        273.0
      ],
      [
        454.0,
        273.0
      ],
      [
        454.0,
        531.0
      ],
      [
        430.0,
        531.0
      ]
    ],
    "text": "",
    "confidence": 0.0
  },
  {
    "bbox": [
      [
        127.0,
        391.0
      ],
      [
        145.0,
        391.0
      ],
      [
        145.0,
        507.0
      ],
      [
        127.0,
        507.0
      ]
    ],
    "text": "",
    "confidence": 0.0
  },
  {
    "bbox": [
      [
        277.0,
        441.0
      ],
      [
        301.0,
        441.0
      ],
      [
        301.0,
        461.0
      ],
      [
        277.0,
        461.0
      ]
    ],
    "text": "明",
    "confidence": 0.08449965664660031
  },
  {
    "bbox": [
      [
        308.0,
        440.0
      ],
      [
        338.0,
        440.0
      ],
      [
        338.0,
        476.0
      ],
      [
        308.0,
        476.0
      ]
    ],
    "text": "布羞",
    "confidence": 0.0018273475498543814
  },
  {
    "bbox": [
      [
        251.0,
        491.0
      ],
      [
        339.0,
        491.0
      ],
      [
        339.0,
        530.0
      ],
      [
        251.0,
        530.0
      ]
    ],
    "text": "酗囤不匠劇罕",
    "confidence": 3.6969647708637947e-06
  },
  {
    "bbox": [
      [
        325.0,
        477.0
      ],
      [
        337.0,
        477.0
      ],
      [
        337.0,
        513.0
      ],
      [
        325.0,
        513.0
      ]
    ],
    "text": "胃",
    "confidence": 0.9567703294107197
  },
  {
    "bbox": [
      [
        406.0,
        442.0
      ],
      [
        430.0,
        442.0
      ],
      [
        430.0,
        530.0
      ],
      [
        406.0,
        530.0
      ]
    ],
    "text": "",
    "confidence": 0.0
  },
  {
    "bbox": [
      [
        529.0,
        459.0
      ],
      [
        565.0,
        459.0
      ],
      [
        565.0,
        535.0
      ],
      [
        529.0,
        535.0
      ]
    ],
    "text": "蘿",
    "confidence": 0.020517101329255105
  }
]