[
  {
    "bbox": [
      [
        323.0,
        95.0
      ],
      [
        349.0,
        95.0
      ],
      [
        349.0,
        113.0
      ],
      [
        323.0,
        113.0
      ]
    ],
    "text": "(叮",
    "confidence": 0.3870081804309065
  },
  {
    "bbox": [
      [
        59.0,
        76.0
      ],
      [
        327.0,
        76.0
      ],
      [
        327.0,
        160.0
      ],
      [
        59.0,
        160.0
      ]
    ],
    "text": "糕苧立鯊 沾",
    "confidence": 2.714750455783501e-06
  },
  {
    "bbox": [
      [
        69.0,
        115.0
      ],
      [
        125.0,
        115.0
      ],
      [
        125.0,
        153.0
      ],
      [
        69.0,
        153.0
      ]
    ],
    "text": "|莢",
    "confidence": 0.0011070187875788253
  },
  {
    "bbox": [
      [
        129.0,
        123.0
      ],
      [
        149.0,
        123.0
      ],
      [
        149.0,
        151.0
      ],
      [
        129.0,
        151.0
      ]
    ],
    "text": "鑿",
    "confidence": 0.00906452148670045
  },
  {
    "bbox": [
      [
        293.0,
        109.0
      ],
      [
        349.0,
        109.0
      ],
      [
        349.0,
        153.0
      ],
      [
        293.0,
        153.0
      ]
    ],
    "text": "釜希",
    "confidence": 0.0019694662368096535
  },
  {
    "bbox": [
      [
        348.0,
        76.0
      ],
      [
        472.0,
        76.0
      ],
      [
        472.0,
        150.0
      ],
      [
        348.0,
        150.0
      ]
    ],
    "text": "蓋森$",
    "confidence": 3.957635448070671e-05
  },
  {
    "bbox": [
      [
        436.0,
        118.0
      ],
      [
        464.0,
        118.0
      ],
      [
        464.0,
        144.0
      ],
      [
        436.0,
        144.0
      ]
    ],
    "text": "#]",
    "confidence": 0.36287493170811624
  },
  {
    "bbox": [
      [
        458.0,
        76.0
      ],
      [
        640.0,
        76.0
      ],
      [
        640.0,
        154.0
      ],
      [
        458.0,
        154.0
      ]
    ],
    "text": "發淞藏茸航荒",
    "confidence": 5.942727625550017e-07
  },
  {
    "bbox": [
      [
        474.0,
        170.0
      ],
      [
        498.0,
        170.0
      ],
      [
        498.0,
        198.0
      ],
      [
        474.0,
        198.0
      ]
    ],
    "text": "暠",
    "confidence": 0.012282410659800791
  },
  {
    "bbox": [
      [
        611.0,
        167.0
      ],
      [
        631.0,
        167.0
      ],
      [
        631.0,
        195.0
      ],
      [
        611.0,
        195.0
      ]
    ],
    "text": "8",
    "confidence": 0.015245599153980438
  },
  {
    "bbox": [
      [
        74.0,
        172.0
      ],
      [
        192.0,
        172.0
      ],
      [
        192.0,
        276.0
      ],
      [
        74.0,
        276.0
      ]
    ],
    "text": "_*#志",
    "confidence": 2.4760778615018353e-05
  },
  {
    "bbox": [
      [
        495.0,
        163.0
      ],
      [
        617.0,
        163.0
      ],
      [
        617.0,
        231.0
      ],
      [
        495.0,
        231.0
      ]
    ],
    "text": "夸\"2",
    "confidence": 7.1020220729915e-05
  },
  {
    "bbox": [
      [
        610.0,
        188.0
      ],
      [
        634.0,
        188.0
      ],
      [
        634.0,
        218.0
      ],
      [
        610.0,
        218.0
      ]
    ],
    "text": "簑",
    "confidence": 0.0037883633752468088
  },
  {
    "bbox": [
      [
        505.0,
        285.0
      ],
      [
        523.0,
        285.0
      ],
      [
        523.0,
        333.0
      ],
      [
        505.0,
        333.0
      ]
    ],
    "text": "3",
    "confidence": 0.33226889117764813
  },
  {
    "bbox": [
      [
        549.0,
        277.0
      ],
      [
        615.0,
        277.0
      ],
      [
        615.0,
        343.0
      ],
      [
        549.0,
        343.0
      ]
    ],
    "text": "笠",
    "confidence": 0.0007326335831198995
  },
  {
    "bbox": [
      [
        324.0,
        376.0
      ],
      [
        350.0,
        376.0
      ],
      [
        350.0,
        494.0
      ],
      [
        324.0,
        494.0
      ]
    ],
    "text": "",
    "confidence": 0.0
  },
  {
    "bbox": [
      [
        443.0,
        421.0
      ],
      [
        463.0,
        421.0
      ],
      [
        463.0,
        475.0
      ],
      [
        443.0,
        475.0
      ]
    ],
    "text": "",
    "confidence": 0.0
  }
]