[
  {
    "bbox": [
      [
        244.0,
        38.0
      ],
      [
        265.0,
        38.0
      ],
      [
        265.0,
        93.0
      ],
      [
        244.0,
        93.0
      ]
    ],
    "text": "士",
    "confidence": 0.26844004848502223
  },
  {
    "bbox": [
      [
        310.0,
        29.0
      ],
      [
        417.0,
        29.0
      ],
      [
        417.0,
        102.0
      ],
      [
        310.0,
        102.0
      ]
    ],
    "text": "1圭",
    "confidence": 0.006425428797814063
  },
  {
    "bbox": [
      [
        491.0,
        35.0
      ],
      [
        516.0,
        35.0
      ],
      [
        516.0,
        90.0
      ],
      [
        491.0,
        90.0
      ]
    ],
    "text": "",
    "confidence": 0.0
  },
  {
    "bbox": [
      [
        563.0,
        30.0
      ],
      [
        629.0,
        30.0
      ],
      [
        629.0,
        97.0
      ],
      [
        563.0,
        97.0
      ]
    ],
    "text": "1",
    "confidence": 0.0011208215825005002
  },
  {
    "bbox": [
      [
        144.0,
        100.0
      ],
      [
        184.0,
        100.0
      ],
      [
        184.0,
        126.0
      ],
      [
        144.0,
        126.0
      ]
    ],
    "text": "沁訃",
    "confidence": 0.11257617786619986
  },
  {
    "bbox": [
      [
        75.0,
        133.0
      ],
      [
        89.0,
        133.0
      ],
      [
        89.0,
        155.0
      ],
      [
        75.0,
        155.0
      ]
    ],
    "text": "|",
    "confidence": 0.00020570970764804963
  },
  {
    "bbox": [
      [
        242.0,
        106.0
      ],
      [
        274.0,
        106.0
      ],
      [
        274.0,
        178.0
      ],
      [
        242.0,
        178.0
      ]
    ],
    "text": "泫",
    "confidence": 0.015519065271780486
  },
  {
    "bbox": [
      [
        304.0,
        99.0
      ],
      [
        456.0,
        99.0
      ],
      [
        456.0,
        204.0
      ],
      [
        304.0,
        204.0
      ]
    ],
    "text": "鬟_",
    "confidence": 0.0003581916084374167
  },
  {
    "bbox": [
      [
        446.0,
        90.0
      ],
      [
        646.0,
        90.0
      ],
      [
        646.0,
        246.0
      ],
      [
        446.0,
        246.0
      ]
    ],
    "text": "錳",
    "confidence": 2.1902336919746518e-05
  },
  {
    "bbox": [
      [
        77.0,
        157.0
      ],
      [
        93.0,
        157.0
      ],
      [
        93.0,
        211.0
      ],
      [
        77.0,
        211.0
      ]
    ],
    "text": "",
    "confidence": 0.0
  },
  {
    "bbox": [
      [
        213.0,
        169.0
      ],
      [
        280.0,
        169.0
      ],
      [
        280.0,
        239.0
      ],
      [
        213.0,
        239.0
      ]
    ],
    "text": "言*",
    "confidence": 0.291376895010235
  },
  {
    "bbox": [
      [
        331.0,
        197.0
      ],
      [
        345.0,
        197.0
      ],
      [
        345.0,
        237.0
      ],
      [
        331.0,
        237.0
      ]
    ],
    "text": "",
    "confidence": 0.0
  },
  {
    "bbox": [
      [
        507.0,
        177.0
      ],
      [
        527.0,
        177.0
      ],
      [
        527.0,
        235.0
      ],
      [
        507.0,
        235.0
      ]
    ],
    "text": "*",
    "confidence": 0.00045978707437391644
  },
  {
    "bbox": [
      [
        617.0,
        199.0
      ],
      [
        635.0,
        199.0
      ],
      [
        635.0,
        231.0
      ],
      [
        617.0,
        231.0
      ]
    ],
    "text": "云",
    "confidence": 0.0036883409309660525
  },
  {
    "bbox": [
      [
        217.0,
        239.0
      ],
      [
        281.0,
        239.0
      ],
      [
        281.0,
        333.0
      ],
      [
        217.0,
        333.0
      ]
    ],
    "text": "",
    "confidence": 0.0
  },
  {
    "bbox": [
      [
        279.0,
        176.0
      ],
      [
        463.0,
        176.0
      ],
      [
        463.0,
        315.0
      ],
      [
        279.0,
        315.0
      ]
    ],
    "text": ";'",
    "confidence": 0.13428999278535567
  },
  {
    "bbox": [
      [
        439.0,
        287.0
      ],
      [
        455.0,
        287.0
      ],
      [
        455.0,
        321.0
      ],
      [
        439.0,
        321.0
      ]
    ],
    "text": "+",
    "confidence": 0.5230011174399465
  },
  {
    "bbox": [
      [
        464.0,
        168.0
      ],
      [
        612.0,
        168.0
      ],
      [
        612.0,
        356.0
      ],
      [
        464.0,
        356.0
      ]
    ],
    "text": "",
    "confidence": 0.0
  },
  {
    "bbox": [
      [
        617.0,
        235.0
      ],
      [
        633.0,
        235.0
      ],
      [
        633.0,
        275.0
      ],
      [
        617.0,
        275.0
      ]
    ],
    "text": "釜",
    "confidence": 0.09116570838571736
  },
  {
    "bbox": [
      [
        261.0,
        309.0
      ],
      [
        277.0,
        309.0
      ],
      [
        277.0,
        337.0
      ],
      [
        261.0,
        337.0
      ]
    ],
    "text": "$",
    "confidence": 0.007357769071770159
  },
  {
    "bbox": [
      [
        61.0,
        443.0
      ],
      [
        119.0,
        443.0
      ],
      [
        119.0,
        487.0
      ],
      [
        61.0,
        487.0
      ]
    ],
    "text": "芒元",
    "confidence": 0.0008539251241432442
  },
  {
    "bbox": [
      [
        137.0,
        441.0
      ],
      [
        151.0,
        441.0
      ],
      [
        151.0,
        477.0
      ],
      [
        137.0,
        477.0
      ]
    ],
    "text": "*",
    "confidence": 0.003138097972207446
  },
  {
    "bbox": [
      [
        63.0,
        483.0
      ],
      [
        77.0,
        483.0
      ],
      [
        77.0,
        527.0
      ],
      [
        63.0,
        527.0
      ]
    ],
    "text": "下",
    "confidence": 0.02832239316802898
  },
  {
    "bbox": [
      [
        115.0,
        477.0
      ],
      [
        157.0,
        477.0
      ],
      [
        157.0,
        531.0
      ],
      [
        115.0,
        531.0
      ]
    ],
    "text": "/",
    "confidence": 0.004903955160674656
  },
  {
    "bbox": [
      [
        65.0,
        523.0
      ],
      [
        79.0,
        523.0
      ],
      [
        79.0,
        547.0
      ],
      [
        65.0,
        547.0
      ]
    ],
    "text": "`",
    "confidence": 0.02881963260763265
  },
  {
    "bbox": [
      [
        275.65440104398374,
        36.030085950707374
      ],
      [
        295.41686798906665,
        34.04392712822566
      ],
      [
        302.34559895601626,
        96.96991404929263
      ],
      [
        281.58313201093335,
        98.95607287177434
      ]
    ],
    "text": "3",
    "confidence": 0.5811195777657794
  },
  {
    "bbox": [
      [
        423.6358214796354,
        34.03343599003108
      ],
      [
        444.82221550621364,
        36.176826486221934
      ],
      [
        441.3641785203646,
        91.96656400996892
      ],
      [
        420.17778449378636,
        90.82317351377806
      ]
    ],
    "text": "孝",
    "confidence": 0.0019466107832778606
  },
  {
    "bbox": [
      [
        454.41165159458546,
        36.05825797292724
      ],
      [
        478.65613437075217,
        32.07263126895198
      ],
      [
        488.58834840541454,
        91.94174202707276
      ],
      [
        464.34386562924783,
        95.92736873104802
      ]
    ],
    "text": "殼",
    "confidence": 0.13034613442386345
  },
  {
    "bbox": [
      [
        532.592091491776,
        39.04203916052479
      ],
      [
        551.3641785203646,
        36.03343599003108
      ],
      [
        559.407908508224,
        90.9579608394752
      ],
      [
        541.6358214796354,
        93.96656400996892
      ]
    ],
    "text": "亡",
    "confidence": 0.0588545763107684
  },
  {
    "bbox": [
      [
        176.90746443890615,
        104.10030797009324
      ],
      [
        218.64835508461053,
        85.03513322158327
      ],
      [
        253.09253556109385,
        169.89969202990676
      ],
      [
        211.35164491538947,
        188.96486677841673
      ]
    ],
    "text": "3",
    "confidence": 0.0001280484102339158
  },
  {
    "bbox": [
      [
        276.52230268352616,
        104.03827663786205
      ],
      [
        299.68711800117666,
        101.07974849499928
      ],
      [
        305.47769731647384,
        171.96172336213795
      ],
      [
        282.31288199882334,
        174.92025150500072
      ]
    ],
    "text": "丸",
    "confidence": 0.0055965391860013924
  },
  {
    "bbox": [
      [
        570.8296807994751,
        106.00726535385853
      ],
      [
        591.199007438042,
        105.00992561958002
      ],
      [
        598.1703192005249,
        226.99273464614146
      ],
      [
        578.800992561958,
        228.99007438041997
      ]
    ],
    "text": "",
    "confidence": 0.0
  }
]