[
  {
    "bbox": [
      [
        62.0,
        58.0
      ],
      [
        174.0,
        58.0
      ],
      [
        174.0,
        90.0
      ],
      [
        62.0,
        90.0
      ]
    ],
    "text": "宓襤戈若",
    "confidence": 8.630613592686132e-05
  },
  {
    "bbox": [
      [
        173.0,
        51.0
      ],
      [
        648.0,
        51.0
      ],
      [
        648.0,
        101.0
      ],
      [
        173.0,
        101.0
      ]
    ],
    "text": "垚之雜訖誌矻迄訖兼齒為訖燹天武芝",
    "confidence": 6.603470945921945e-09
  },
  {
    "bbox": [
      [
        179.0,
        87.0
      ],
      [
        203.0,
        87.0
      ],
      [
        203.0,
        107.0
      ],
      [
        179.0,
        107.0
      ]
    ],
    "text": "仕",
    "confidence": 0.9723075518218707
  },
  {
    "bbox": [
      [
        210.0,
        87.0
      ],
      [
        352.0,
        87.0
      ],
      [
        352.0,
        116.0
      ],
      [
        210.0,
        116.0
      ]
    ],
    "text": "; 迪父人輝",
    "confidence": 0.00039941360496775655
  },
  {
    "bbox": [
      [
        565.0,
        93.0
      ],
      [
        645.0,
        93.0
      ],
      [
        645.0,
        113.0
      ],
      [
        565.0,
        113.0
      ]
    ],
    "text": "女女 廷",
    "confidence": 0.1318507343530655
  },
  {
    "bbox": [
      [
        92.0,
        102.0
      ],
      [
        150.0,
        102.0
      ],
      [
        150.0,
        132.0
      ],
      [
        92.0,
        132.0
      ]
    ],
    "text": "汪幹",
    "confidence": 0.23869661051265512
  },
  {
    "bbox": [
      [
        151.0,
        101.0
      ],
      [
        271.0,
        101.0
      ],
      [
        271.0,
        145.0
      ],
      [
        151.0,
        145.0
      ]
    ],
    "text": "蘧草雲鑫",
    "confidence": 5.576951298280619e-05
  },
  {
    "bbox": [
      [
        356.0,
        114.0
      ],
      [
        388.0,
        114.0
      ],
      [
        388.0,
        138.0
      ],
      [
        356.0,
        138.0
      ]
    ],
    "text": "札",
    "confidence": 0.2561342526874455
  },
  {
    "bbox": [
      [
        357.0,
        86.0
      ],
      [
        648.0,
        86.0
      ],
      [
        648.0,
        143.0
      ],
      [
        357.0,
        143.0
      ]
    ],
    "text": "枇琵尤逸棄籌 塗崩柔",
    "confidence": 9.07679254876138e-07
  },
  {
    "bbox": [
      [
        214.0,
        128.0
      ],
      [
        240.0,
        128.0
      ],
      [
        240.0,
        166.0
      ],
      [
        214.0,
        166.0
      ]
    ],
    "text": "云",
    "confidence": 0.23942803486312414
  },
  {
    "bbox": [
      [
        425.0,
        145.0
      ],
      [
        445.0,
        145.0
      ],
      [
        445.0,
        173.0
      ],
      [
        425.0,
        173.0
      ]
    ],
    "text": "坐",
    "confidence": 0.0035184543645014887
  },
  {
    "bbox": [
      [
        461.0,
        141.0
      ],
      [
        475.0,
        141.0
      ],
      [
        475.0,
        187.0
      ],
      [
        461.0,
        187.0
      ]
    ],
    "text": "筊",
    "confidence": 0.14243731423025352
  },
  {
    "bbox": [
      [
        508.0,
        130.0
      ],
      [
        566.0,
        130.0
      ],
      [
        566.0,
        180.0
      ],
      [
        508.0,
        180.0
      ]
    ],
    "text": "塞產",
    "confidence": 0.0006108993597017861
  },
  {
    "bbox": [
      [
        573.0,
        147.0
      ],
      [
        593.0,
        147.0
      ],
      [
        593.0,
        173.0
      ],
      [
        573.0,
        173.0
      ]
    ],
    "text": "(",
    "confidence": 0.006448183860676915
  },
  {
    "bbox": [
      [
        598.0,
        134.0
      ],
      [
        622.0,
        134.0
      ],
      [
        622.0,
        200.0
      ],
      [
        598.0,
        200.0
      ]
    ],
    "text": "芸",
    "confidence": 0.0038288559277722123
  },
  {
    "bbox": [
      [
        61.0,
        84.0
      ],
      [
        130.0,
        84.0
      ],
      [
        130.0,
        357.0
      ],
      [
        61.0,
        357.0
      ]
    ],
    "text": "",
    "confidence": 0.0
  },
  {
    "bbox": [
      [
        128.0,
        128.0
      ],
      [
        154.0,
        128.0
      ],
      [
        154.0,
        220.0
      ],
      [
        128.0,
        220.0
      ]
    ],
    "text": "",
    "confidence": 0.0
  },
  {
    "bbox": [
      [
        131.0,
        241.0
      ],
      [
        151.0,
        241.0
      ],
      [
        151.0,
        289.0
      ],
      [
        131.0,
        289.0
      ]
    ],
    "text": "!",
    "confidence": 8.384949118592569e-05
  },
  {
    "bbox": [
      [
        139.0,
        93.0
      ],
      [
        416.0,
        93.0
      ],
      [
        416.0,
        347.0
      ],
      [
        139.0,
        347.0
      ]
    ],
    "text": "",
    "confidence": 0.0
  },
  {
    "bbox": [
      [
        373.0,
        263.0
      ],
      [
        391.0,
        263.0
      ],
      [
        391.0,
        295.0
      ],
      [
        373.0,
        295.0
      ]
    ],
    "text": "_",
    "confidence": 0.0026660998340238273
  },
  {
    "bbox": [
      [
        397.0,
        133.0
      ],
      [
        422.0,
        133.0
      ],
      [
        422.0,
        240.0
      ],
      [
        397.0,
        240.0
      ]
    ],
    "text": "",
    "confidence": 0.0
  },
  {
    "bbox": [
      [
        401.0,
        239.0
      ],
      [
        421.0,
        239.0
      ],
      [
        421.0,
        265.0
      ],
      [
        401.0,
        265.0
      ]
    ],
    "text": "7=",
    "confidence": 0.004794838612384395
  },
  {
    "bbox": [
      [
        467.0,
        121.0
      ],
      [
        660.0,
        121.0
      ],
      [
        660.0,
        354.0
      ],
      [
        467.0,
        354.0
      ]
    ],
    "text": "慵",
    "confidence": 0.0002694806595454659
  },
  {
    "bbox": [
      [
        335.0,
        271.0
      ],
      [
        353.0,
        271.0
      ],
      [
        353.0,
        313.0
      ],
      [
        335.0,
        313.0
      ]
    ],
    "text": "篠",
    "confidence": 0.0005987096880852999
  },
  {
    "bbox": [
      [
        281.0,
        277.0
      ],
      [
        301.0,
        277.0
      ],
      [
        301.0,
        361.0
      ],
      [
        281.0,
        361.0
      ]
    ],
    "text": "",
    "confidence": 0.0
  },
  {
    "bbox": [
      [
        307.0,
        297.0
      ],
      [
        327.0,
        297.0
      ],
      [
        327.0,
        335.0
      ],
      [
        307.0,
        335.0
      ]
    ],
    "text": "髻",
    "confidence": 0.2100516967084909
  },
  {
    "bbox": [
      [
        61.0,
        364.0
      ],
      [
        358.0,
        364.0
      ],
      [
        358.0,
        429.0
      ],
      [
        61.0,
        429.0
      ]
    ],
    "text": "全全全金余全全全^裘",
    "confidence": 9.518673138935546e-05
  },
  {
    "bbox": [
      [
        360.0,
        376.0
      ],
      [
        644.0,
        376.0
      ],
      [
        644.0,
        404.0
      ],
      [
        360.0,
        404.0
      ]
    ],
    "text": "//////4/4/么",
    "confidence": 0.029180324827346
  },
  {
    "bbox": [
      [
        159.0,
        405.0
      ],
      [
        181.0,
        405.0
      ],
      [
        181.0,
        419.0
      ],
      [
        159.0,
        419.0
      ]
    ],
    "text": "工",
    "confidence": 0.7556152501074997
  },
  {
    "bbox": [
      [
        215.0,
        403.0
      ],
      [
        237.0,
        403.0
      ],
      [
        237.0,
        419.0
      ],
      [
        215.0,
        419.0
      ]
    ],
    "text": "上",
    "confidence": 0.9312619916536313
  },
  {
    "bbox": [
      [
        423.0,
        403.0
      ],
      [
        447.0,
        403.0
      ],
      [
        447.0,
        417.0
      ],
      [
        423.0,
        417.0
      ]
    ],
    "text": "-",
    "confidence": 0.5923772434982766
  },
  {
    "bbox": [
      [
        331.0,
        419.0
      ],
      [
        351.0,
        419.0
      ],
      [
        351.0,
        453.0
      ],
      [
        331.0,
        453.0
      ]
    ],
    "text": "鋪",
    "confidence": 0.00018093019586239937
  }
]